funcx/__init__.py
funcx/version.py
funcx/sdk/__init__.py
funcx/sdk/client.py
funcx/sdk/executor.py
funcx/sdk/web_client.py
funcx/sdk/login_manager/__init__.py
funcx/serialize/__init__.py
funcx-2.4.0.dist-info/LICENSE
funcx-2.4.0.dist-info/METADATA
funcx-2.4.0.dist-info/WHEEL
funcx-2.4.0.dist-info/top_level.txt
funcx-2.4.0.dist-info/RECORD
