Metadata-Version: 2.1
Name: funcx
Version: 2.4.0
Summary: Globus Compute: High Performance Function Serving for Science
Home-page: https://github.com/funcx-faas/funcx
Author: The Globus Compute Team
Author-email: support@globus.org
License: Apache License, Version 2.0
Project-URL: Changelog, https://globus-compute.readthedocs.io/en/latest/changelog.html
Project-URL: Upgrade to Globus Compute, https://globus-compute.readthedocs.io/en/latest/funcx_upgrade.html
Keywords: funcX,FaaS,Function Serving,Globus Compute
Classifier: Development Status :: 3 - Alpha
Classifier: Intended Audience :: Science/Research
Classifier: License :: OSI Approved :: Apache Software License
Classifier: Natural Language :: English
Classifier: Operating System :: OS Independent
Classifier: Programming Language :: Python :: 3
Classifier: Topic :: Scientific/Engineering
Requires-Python: >=3.7
License-File: LICENSE
Requires-Dist: globus-compute-sdk ==2.4.0
